dim/__init__.py
dim/__version__.py
dim/dim.py
dim_python-0.1.1.dist-info/LICENSE
dim_python-0.1.1.dist-info/WHEEL
dim_python-0.1.1.dist-info/METADATA
dim_python-0.1.1.dist-info/RECORD
