Metadata-Version: 2.1
Name: dim-python
Version: 0.1.1
Summary: Python implementation of dim (Data Installation Manager): Manage open data in your projects, like a package manager.
Home-page: https://github.com/c-3lab/dim-python/
License: MIT
Keywords: open-data,dataops,data science,datasets
Author: C3Lab
Author-email: info.c3lab@gmail.com
Requires-Python: >=3.8,<4.0
Classifier: Development Status :: 2 - Pre-Alpha
Classifier: License :: OSI Approved :: MIT License
Classifier: Programming Language :: Python :: 3
Classifier: Programming Language :: Python :: 3.8
Classifier: Programming Language :: Python :: 3.9
Classifier: Programming Language :: Python :: 3.10
Classifier: Programming Language :: Python :: 3.11
Classifier: Programming Language :: Python :: 3.10
Classifier: Programming Language :: Python :: 3.8
Classifier: Programming Language :: Python :: 3.9
Classifier: Topic :: Database
Requires-Dist: requests (>=2.28.1,<3.0.0)
Project-URL: Documentation, https://github.com/c-3lab/dim-python/README.md
Project-URL: Repository, https://github.com/c-3lab/dim-python/
